{
  "type": "spell",
  "name": "Conjuration of the Indubitable Cold",
  "system": {
    "technique": {
      "value": "pe"
    },
    "form": {
      "value": "ig"
    },
    "baseLevel": 4,
    "range": {
      "value": "voice"
    },
    "duration": {
      "value": "moment"
    },
    "target": {
      "value": "part"
    },
    "targetSize": 2,
    "complexity": 0,
    "ritual": false,
    "technique-req": {
      "cr": false,
      "in": false,
      "mu": false,
      "pe": false,
      "re": false
    },
    "form-req": {
      "an": false,
      "aq": false,
      "au": false,
      "co": false,
      "he": false,
      "ig": false,
      "im": false,
      "me": false,
      "te": false,
      "vi": false
    },
    "description": "Cools the air within ten paces of the target, leaving it slightly below freezing. All nonliving things are chilled thoroughly, not just on the surface. All living things (except you, if you cast with a Rego requisite) lose one Fatigue level. House fires become as small as campfires, bonfires become as small as torch fires, and campfires and smaller fires go out.",
    "source": "ArM5",
    "page": 142,
    "indexKey": "conjuration-of-the-indubitable-cold",
    "enhancingRequisite": 0,
    "general": false,
    "levelOffset": 0,
    "baseEffectDescription": "",
    "applyFocus": false,
    "bonus": 0,
    "bonusDesc": "",
    "xp": 0,
    "masteryAbilities": "",
    "review_status": "toReview",
    "reviewer": "",
    "ownership": null,
    "level": 25
  },
  "img": "systems/arm5e/assets/magic/ig.png",
  "effects": [],
  "flags": {},
  "_stats": {
    "compendiumSource": null,
    "duplicateSource": null,
    "coreVersion": "13.351",
    "systemId": "arm5e",
    "systemVersion": "2.4.0.4",
    "createdTime": 1730266564295,
    "modifiedTime": 1752180698200,
    "lastModifiedBy": "ErQ613O32LNYb71L",
    "exportSource": null
  },
  "_id": "tjruQAaMdYlzpUfz",
  "folder": "TXWRpVwDyXc4LXyP",
  "sort": 0,
  "ownership": {
    "default": 0,
    "6SdI10VpXHcBvx2J": 3
  },
  "_key": "!items!tjruQAaMdYlzpUfz"
}
