{
  "folder": "zbXsj4TBQ7fnb7ME",
  "name": "Ablating",
  "type": "virtue",
  "img": "systems/arm5e/assets/icons/upgraded-magic.svg",
  "system": {
    "description": "<p><span class=\"fontstyle0\">When combined with Summoning, Ablating allows a sorcerer to leech away the power of a demon or other spirit for his own. This Virtue opens the Ablating Art for him at 0, the mechanics of which are found in Chapter 11: Ars Goetia.</span></p>",
    "source": "RoP:I",
    "page": 82,
    "indexKey": "ablating",
    "review_status": "toReview",
    "reviewer": "",
    "credits": "",
    "type": "other",
    "impact": {
      "value": "major"
    },
    "hidden": false,
    "tainted": false
  },
  "effects": [
    {
      "origin": "Item.ct1lS3gA7fJC2NMS",
      "duration": {
        "turns": null,
        "startTime": null,
        "seconds": null,
        "combat": null,
        "rounds": null,
        "startRound": null,
        "startTurn": null
      },
      "disabled": false,
      "tint": "#000000",
      "changes": [
        {
          "key": "system.bonuses.skills.supernatural_ablating.xpMod",
          "value": "5",
          "mode": 2,
          "priority": null
        }
      ],
      "flags": {
        "arm5e": {
          "type": [
            "xpBonusSupernaturalAbility"
          ],
          "subtype": [
            "supernatural"
          ],
          "option": [
            "ablating"
          ],
          "hidden": false
        }
      },
      "name": "Xp Bonus",
      "img": "icons/svg/aura.svg",
      "_id": "CePDfz7wTDh0qnbQ",
      "type": "base",
      "system": {},
      "description": "",
      "transfer": true,
      "statuses": [],
      "sort": 0,
      "_stats": {
        "compendiumSource": null,
        "duplicateSource": null,
        "coreVersion": "13.351",
        "systemId": "arm5e",
        "systemVersion": "2.4.0.16",
        "createdTime": null,
        "modifiedTime": null,
        "lastModifiedBy": null,
        "exportSource": null
      },
      "_key": "!items.effects!ct1lS3gA7fJC2NMS.CePDfz7wTDh0qnbQ"
    }
  ],
  "flags": {},
  "_stats": {
    "compendiumSource": null,
    "duplicateSource": null,
    "coreVersion": "13.351",
    "systemId": "arm5e",
    "systemVersion": "2.4.0.16",
    "createdTime": 1757740088763,
    "modifiedTime": 1757740088763,
    "lastModifiedBy": "6SdI10VpXHcBvx2J",
    "exportSource": null
  },
  "_id": "ct1lS3gA7fJC2NMS",
  "sort": 0,
  "ownership": {
    "default": 0,
    "6SdI10VpXHcBvx2J": 3
  },
  "_key": "!items!ct1lS3gA7fJC2NMS"
}
