{
  "name": "Cailleleach Magic",
  "type": "virtue",
  "img": "systems/arm5e/assets/icons/VF/supernatural.svg",
  "system": {
    "description": "<p><span class=\"fontstyle0\">The character’s gruagach tradition has incorporated aspects of the followers of Cailleach, the Pictish earth goddess and companion to Gruagach. When the character casts a spontaneous spell, the lowest applicable Art is doubled before the casting total is divided by two.</span> </p>",
    "source": "HMRE",
    "page": 56,
    "indexKey": "caillelach-magic",
    "review_status": "toReview",
    "reviewer": "",
    "credits": "",
    "type": "supernatural",
    "impact": {
      "value": "major"
    },
    "hidden": false,
    "tainted": false
  },
  "effects": [],
  "folder": "ZFzMK6RgEkGopaas",
  "flags": {},
  "_stats": {
    "compendiumSource": null,
    "duplicateSource": null,
    "coreVersion": "13.351",
    "systemId": "arm5e",
    "systemVersion": "2.4.0.16",
    "createdTime": 1757739626053,
    "modifiedTime": 1757739626053,
    "lastModifiedBy": "6SdI10VpXHcBvx2J",
    "exportSource": null
  },
  "_id": "YBSYkAM8ZVadvn2S",
  "sort": 0,
  "ownership": {
    "default": 0,
    "6SdI10VpXHcBvx2J": 3
  },
  "_key": "!items!YBSYkAM8ZVadvn2S"
}
