{
  "name": "Cautious Sorcerer",
  "type": "virtue",
  "img": "systems/arm5e/assets/icons/VF/hermetic.svg",
  "effects": [],
  "flags": {
    "core": {},
    "cf": {
      "id": "temp_nxctmjlqqdb",
      "path": "Virtues#/CF_SEP/Hermetic",
      "color": "#000000"
    }
  },
  "system": {
    "description": "<p>You are very careful with magic, and are less likely to fail spectacularly if you do fail. You roll three fewer botch dice when casting spells (whether ritual, formulaic, or spontaneous), and when working in the laboratory. This Virtue may not reduce the number of botch dice rolled below one. However, its effects are applied before any other effects which reduce botch dice, such as Spell Mastery (see page @@), and they may reduce the number of botch dice to zero.</p><p> </p>",
    "source": "ArM5Def",
    "page": 0,
    "type": "hermetic",
    "impact": {
      "value": "minor"
    },
    "indexKey": "cautious-sorcerer",
    "review_status": "needAE",
    "reviewer": "xzotl",
    "hidden": false
  },
  "_stats": {
    "compendiumSource": null,
    "duplicateSource": null,
    "coreVersion": "12.331",
    "systemId": "arm5e",
    "systemVersion": "2.3.2.5",
    "createdTime": 1729316634167,
    "modifiedTime": 1730454066531,
    "lastModifiedBy": "6SdI10VpXHcBvx2J"
  },
  "folder": "C8jqPqfblXk6hGCE",
  "_id": "bfQCFMniVB6m9xwZ",
  "sort": 2900000,
  "ownership": {
    "default": 0,
    "6SdI10VpXHcBvx2J": 3
  },
  "_key": "!items!bfQCFMniVB6m9xwZ"
}
