{
  "folder": "MewGclJOm3EmdeRI",
  "name": "Survive Without Water",
  "type": "quality",
  "img": "systems/arm5e/assets/icons/VF/generalVirtue.svg",
  "system": {
    "description": "<p>The creature can survive without water for up to two weeks.</p>",
    "source": "ArM5Def",
    "page": 0,
    "indexKey": "survive-without-water",
    "review_status": "reviewed",
    "reviewer": "xzotl",
    "type": "mundane",
    "impact": {
      "value": "minor"
    },
    "hidden": false,
    "tainted": false
  },
  "effects": [],
  "ownership": {
    "default": 0,
    "wUH1ww0o0zQEBtKr": 3
  },
  "flags": {},
  "_stats": {
    "compendiumSource": null,
    "duplicateSource": null,
    "coreVersion": "13.351",
    "systemId": "arm5e",
    "systemVersion": "2.3.2.11",
    "createdTime": 1733252238645,
    "modifiedTime": 1733252750707,
    "lastModifiedBy": "wUH1ww0o0zQEBtKr",
    "exportSource": null
  },
  "_id": "Ptz6SP4XzykW3frY",
  "sort": 100000,
  "_key": "!items!Ptz6SP4XzykW3frY"
}
