{
  "folder": "k0vela35v1xs3g2S",
  "name": "Hermetic Services",
  "type": "flaw",
  "img": "systems/arm5e/assets/icons/base-magic.svg",
  "system": {
    "description": "<p>A handful of covenants survive by providing resources to other covenants. These resources include goods, like special inks and vis, and services, like creating longevity effects. These covenants are particularly dependent on Hermetic peace for their prosperity, which forces them to act as conciliators in difficult situations.</p>",
    "source": "Cov",
    "page": 21,
    "indexKey": "hermetic-services",
    "review_status": "reviewed",
    "reviewer": "LICHEN",
    "type": "covenantExternalRelations",
    "impact": {
      "value": "major"
    },
    "hidden": false,
    "tainted": false
  },
  "effects": [],
  "flags": {},
  "_stats": {
    "compendiumSource": null,
    "duplicateSource": null,
    "coreVersion": "12.343",
    "systemId": "arm5e",
    "systemVersion": "2.4.0.4",
    "createdTime": 1749287868926,
    "modifiedTime": 1749370310647,
    "lastModifiedBy": "xMd6zrGNn4dbQYey"
  },
  "_id": "wpfQkEIxQpBtVW6Z",
  "sort": 0,
  "ownership": {
    "default": 0,
    "6SdI10VpXHcBvx2J": 3
  },
  "_key": "!items!wpfQkEIxQpBtVW6Z"
}
