{
  "name": "Menagerie",
  "type": "virtue",
  "img": "systems/arm5e/assets/icons/upgraded-magic.svg",
  "system": {
    "description": "",
    "source": "Cov",
    "page": 115,
    "type": "laboratoryOutfitting",
    "impact": {
      "value": "minor"
    }
  },
  "effects": [
    {
      "icon": "icons/svg/aura.svg",
      "origin": "Item.lFPPbERiGoGTmk2Q",
      "duration": {
        "startTime": null,
        "seconds": null,
        "combat": null,
        "rounds": null,
        "turns": null,
        "startRound": null,
        "startTurn": null
      },
      "disabled": false,
      "tint": "#000000",
      "changes": [
        {
          "key": "system.upkeep.bonus",
          "value": "1",
          "mode": 2,
          "priority": null
        },
        {
          "key": "system.safety.bonus",
          "value": "-1",
          "mode": 2,
          "priority": null
        },
        {
          "key": "system.aesthetics.bonus",
          "value": "-1",
          "mode": 2,
          "priority": null
        },
        {
          "mode": 2,
          "key": "system.specialty.an.bonus",
          "value": "2",
          "priority": null
        }
      ],
      "flags": {
        "arm5e": {
          "type": [
            "laboratory",
            "laboratory",
            "laboratory",
            "labSpecialty"
          ],
          "subtype": [
            "upkeep",
            "safety",
            "aesthetics",
            "an"
          ],
          "option": [
            null,
            null,
            null,
            null
          ]
        }
      },
      "_id": "2HA2amcPmuR2jGzd",
      "transfer": true,
      "name": "Menagerie",
      "description": "",
      "statuses": [],
      "_key": "!items.effects!lFPPbERiGoGTmk2Q.2HA2amcPmuR2jGzd"
    }
  ],
  "flags": {
    "cf": {
      "id": "temp_rzez68dypd"
    },
    "core": {
      "sourceId": "Compendium.arm5e.lab-virtues.lFPPbERiGoGTmk2Q"
    }
  },
  "_stats": {
    "systemId": "arm5e",
    "systemVersion": "2.2.2.10",
    "coreVersion": "11.308",
    "createdTime": 1663053848415,
    "modifiedTime": 1693635052182,
    "lastModifiedBy": "quXJxwb9vsFdyJ6l"
  },
  "_id": "lFPPbERiGoGTmk2Q",
  "folder": null,
  "sort": 0,
  "ownership": {
    "default": 0,
    "NGzrSiVnGM6Psvg4": 3
  },
  "_key": "!items!lFPPbERiGoGTmk2Q"
}
