{
  "folder": "gSyknOm0jOHmD6G4",
  "name": "Inhuman Residents",
  "type": "virtue",
  "img": "systems/arm5e/assets/icons/VF/generalFlaw.svg",
  "system": {
    "description": "<p>The majority of the residents of the covenant are inhuman. They have abilities that exceed those of mortals in a useful way. Some covenants house faeries, spirits, ghosts, and awakened animals. The covenant of Calebais is an excellent example of this Boon taken multiple times.</p>",
    "source": "Cov",
    "page": 18,
    "indexKey": "inhuman-residents",
    "review_status": "reviewed",
    "reviewer": "lichen",
    "type": "covenantResidents",
    "impact": {
      "value": "minor"
    },
    "hidden": false,
    "tainted": false
  },
  "effects": [],
  "flags": {},
  "_stats": {
    "compendiumSource": null,
    "duplicateSource": null,
    "coreVersion": "12.343",
    "systemId": "arm5e",
    "systemVersion": "2.4.0.4",
    "createdTime": 1751015903896,
    "modifiedTime": 1751016071818,
    "lastModifiedBy": "6SdI10VpXHcBvx2J"
  },
  "_id": "tegoyMieZLHlTLUa",
  "sort": 0,
  "ownership": {
    "default": 0,
    "6SdI10VpXHcBvx2J": 3
  },
  "_key": "!items!tegoyMieZLHlTLUa"
}
