{
  "folder": "f6ksXHGP47jPAIw9",
  "name": "Unnatural Law",
  "type": "virtue",
  "img": "systems/arm5e/assets/icons/VF/generalFlaw.svg",
  "system": {
    "description": "<p>Within the covenant’s aura, a series of natural laws are suspended. For example, in the Covenant of the Castle of Fees, glass is as durable and hard as iron, and is used as a building material and armament. In the Covenant of the Solemn Scholars, children are able to fly until they lose their virginity. </p><p>This Boon is suitable for covenants that want to play against genre. For example, there is a covenant powered by wonderful machines copied from the works of Heron of Alexandria. These steam rotators permit the covenant to manufacture many other wondrous devices, which fail to work if taken from the covenant. It also allows the troupe to strongly contrast the home of the magi to the mundane world.</p>",
    "source": "Cov",
    "page": 8,
    "indexKey": "",
    "review_status": "reviewed",
    "reviewer": "lichen",
    "type": "covenantSite",
    "impact": {
      "value": "minor"
    },
    "hidden": false,
    "tainted": false
  },
  "effects": [],
  "flags": {},
  "_stats": {
    "compendiumSource": null,
    "duplicateSource": null,
    "coreVersion": "12.343",
    "systemId": "arm5e",
    "systemVersion": "2.4.0.4",
    "createdTime": 1748672301797,
    "modifiedTime": 1748672301797,
    "lastModifiedBy": "ErQ613O32LNYb71L"
  },
  "_id": "wxywXxokCEGOYzmY",
  "sort": 0,
  "ownership": {
    "default": 0,
    "ErQ613O32LNYb71L": 3
  },
  "_key": "!items!wxywXxokCEGOYzmY"
}
